osxmetadata/__init__.py
osxmetadata/__main__.py
osxmetadata/_version.py
osxmetadata/attribute_data/README.md
osxmetadata/attribute_data/__init__.py
osxmetadata/attribute_data/audio_attributes.json
osxmetadata/attribute_data/common_attributes.json
osxmetadata/attribute_data/filesystem_attributes.json
osxmetadata/attribute_data/image_attributes.json
osxmetadata/attribute_data/load_attribute_data.py
osxmetadata/attribute_data/mdimporter_constants.json
osxmetadata/attribute_data/nsurl_resource_keys.json
osxmetadata/attribute_data/video_attributes.json
osxmetadata/backup.py
osxmetadata/constants.py
osxmetadata/datetime_utils.py
osxmetadata/debug.py
osxmetadata/finder_comment.py
osxmetadata/finder_info.py
osxmetadata/finder_tags.py
osxmetadata/mditem.py
osxmetadata/nsurl_metadata.py
osxmetadata/osxmetadata.py
osxmetadata-1.3.5.dist-info/LICENSE
osxmetadata-1.3.5.dist-info/METADATA
osxmetadata-1.3.5.dist-info/WHEEL
osxmetadata-1.3.5.dist-info/entry_points.txt
osxmetadata-1.3.5.dist-info/RECORD
