Metadata-Version: 2.1
Name: osxmetadata
Version: 1.3.5
Summary: Read and write meta data, such as tags/keywords, Finder comments, etc. on MacOS files
Home-page: https://github.com/RhetTbull/osxmetadata
License: MIT
Keywords: cli,mac,macos,metadata,tags,osx,spotlight,extended_attributes
Author: Rhet Turnbull
Author-email: rturnbull+git@gmail.com
Requires-Python: >=3.8,<3.13
Classifier: License :: OSI Approved :: MIT License
Classifier: Programming Language :: Python :: 3
Classifier: Programming Language :: Python :: 3.8
Classifier: Programming Language :: Python :: 3.9
Classifier: Programming Language :: Python :: 3.10
Classifier: Programming Language :: Python :: 3.11
Classifier: Programming Language :: Python :: 3.12
Requires-Dist: bitstring (>=4.2.3,<5.0.0)
Requires-Dist: click (>=8.0,<9.0)
Requires-Dist: py-applescript (>=1.0.3,<2.0.0)
Requires-Dist: pyobjc-core (>=9.0.0)
Requires-Dist: pyobjc-framework-AVFoundation (>=9.0.0)
Requires-Dist: pyobjc-framework-AppleScriptKit (>=9.0.0)
Requires-Dist: pyobjc-framework-AppleScriptObjC (>=9.0.0)
Requires-Dist: pyobjc-framework-CoreMedia (>=9.0.0)
Requires-Dist: pyobjc-framework-CoreServices (>=9.0.0)
Requires-Dist: pyobjc-framework-Quartz (>=9.0.0)
Requires-Dist: pyobjc-framework-ScriptingBridge (>=9.0.0)
Requires-Dist: wheel (>=0.41.2)
Requires-Dist: xattr (>=0.10.1)
Project-URL: Repository, https://github.com/RhetTbull/osxmetadata
